pocketchemist_nmr/__init__.py
pocketchemist_nmr/config.py
pocketchemist_nmr/cli/__init__.py
pocketchemist_nmr/cli/gui.py
pocketchemist_nmr/cli/hookimpls.py
pocketchemist_nmr/cli/nmrpipe.py
pocketchemist_nmr/filters/__init__.py
pocketchemist_nmr/filters/bruker.py
pocketchemist_nmr/gui/__init__.py
pocketchemist_nmr/gui/constants.py
pocketchemist_nmr/gui/funcs.py
pocketchemist_nmr/gui/nmrdesk.py
pocketchemist_nmr/gui/plot_widgets.py
pocketchemist_nmr/processors/__init__.py
pocketchemist_nmr/processors/fileio.py
pocketchemist_nmr/processors/processor.py
pocketchemist_nmr/spectra/__init__.py
pocketchemist_nmr/spectra/constants.py
pocketchemist_nmr/spectra/meta.py
pocketchemist_nmr/spectra/nmr_spectrum.py
pocketchemist_nmr/spectra/utils.py
pocketchemist_nmr/spectra/nmrpipe/__init__.py
pocketchemist_nmr/spectra/nmrpipe/constants.py
pocketchemist_nmr/spectra/nmrpipe/definitions.py
pocketchemist_nmr/spectra/nmrpipe/fileio.py
pocketchemist_nmr/spectra/nmrpipe/meta.py
pocketchemist_nmr/spectra/nmrpipe/nmrpipe_spectrum.py
pocketchemist_nmr-0.2.1.dist-info/METADATA
pocketchemist_nmr-0.2.1.dist-info/WHEEL
pocketchemist_nmr-0.2.1.dist-info/entry_points.txt
pocketchemist_nmr-0.2.1.dist-info/top_level.txt
pocketchemist_nmr-0.2.1.dist-info/RECORD
